README.md
setup.py
cropgbm/Engine.py
cropgbm/Feature.py
cropgbm/Parameters.py
cropgbm/Preprocessed_Geno.py
cropgbm/Preprocessed_Pheno.py
cropgbm/Structure.py
cropgbm/Visualize.py
cropgbm/__init__.py
cropgbm/main.py
cropgbm/run_test.py
cropgbm.egg-info/PKG-INFO
cropgbm.egg-info/SOURCES.txt
cropgbm.egg-info/dependency_links.txt
cropgbm.egg-info/entry_points.txt
cropgbm.egg-info/requires.txt
cropgbm.egg-info/top_level.txt
cropgbm/testdata/configfile.params
cropgbm/testdata/genofile.bed
cropgbm/testdata/genofile.bim
cropgbm/testdata/genofile.fam
cropgbm/testdata/genofile.map
cropgbm/testdata/genofile.ped
cropgbm/testdata/ksampleid_file.txt
cropgbm/testdata/ksnpid_file.txt
cropgbm/testdata/phefile.txt
cropgbm/testdata/rsampleid_file.txt
cropgbm/testdata/rsnpid_file.txt
cropgbm/testdata/test.geno
cropgbm/testdata/test.phe
cropgbm/testdata/test_class.phe
cropgbm/testdata/train.geno
cropgbm/testdata/train.phe
cropgbm/testdata/train_class.phe
cropgbm/testdata/valid.geno
cropgbm/testdata/valid.phe
cropgbm/testdata/valid_class.phe