Metadata-Version: 1.2
Name: cropgbm
Version: 1.1.2
Summary: Crop Genomic Breeding machine (CropGBM) is a multifunctional program that integrates data preprocessing, population structure analysis, SNP selection, phenotype prediction, and data visualization.
Home-page: https://github.com/YuetongXU/CropGBM
Author: Yuetong Xu, Jun Yan
Author-email: cau_cab_xu@163.com
Maintainer: Yuetong Xu
Maintainer-email: cau_cab_xu@163.com
License: MIT License
Platform: all
Classifier: Operating System :: OS Independent
Classifier: License :: OSI Approved :: MIT License
Classifier: Programming Language :: Python :: 3
Requires-Python: >=3
